{"packages/timezone/data/2019a.tzf":["packages/timezone/data/2019a.tzf"],"packages/cupertino_icons/assets/CupertinoIcons.ttf":["packages/cupertino_icons/assets/CupertinoIcons.ttf"],"fonts/DancingScript-Bold.ttf":["fonts/DancingScript-Bold.ttf"],"fonts/DancingScript-Regular.ttf":["fonts/DancingScript-Regular.ttf"],"graphics/IPSView_512_r10.png":["graphics/IPSView_512_r10.png"],"graphics/ImageNotFound_128.png":["graphics/ImageNotFound_128.png"],"fonts/IndieFlower-Regular.ttf":["fonts/IndieFlower-Regular.ttf"],"fonts/OpenSans-Bold.ttf":["fonts/OpenSans-Bold.ttf"],"fonts/OpenSans-BoldItalic.ttf":["fonts/OpenSans-BoldItalic.ttf"],"fonts/OpenSans-Regular.ttf":["fonts/OpenSans-Regular.ttf"],"fonts/OpenSans-RegularItalic.ttf":["fonts/OpenSans-RegularItalic.ttf"],"fonts/PTSans-Bold.ttf":["fonts/PTSans-Bold.ttf"],"fonts/PTSans-BoldItalic.ttf":["fonts/PTSans-BoldItalic.ttf"],"fonts/PTSans-Regular.ttf":["fonts/PTSans-Regular.ttf"],"fonts/PTSans-RegularItalic.ttf":["fonts/PTSans-RegularItalic.ttf"],"fonts/RobotoMono-Bold.ttf":["fonts/RobotoMono-Bold.ttf"],"fonts/RobotoMono-BoldItalic.ttf":["fonts/RobotoMono-BoldItalic.ttf"],"fonts/RobotoMono-Regular.ttf":["fonts/RobotoMono-Regular.ttf"],"fonts/RobotoMono-RegularItalic.ttf":["fonts/RobotoMono-RegularItalic.ttf"]}